zonefinder/__init__.py
zonefinder/core.py
zonefinder-0.0.5.dist-info/licenses/LICENCE
zonefinder-0.0.5.dist-info/METADATA
zonefinder-0.0.5.dist-info/WHEEL
zonefinder-0.0.5.dist-info/top_level.txt
zonefinder-0.0.5.dist-info/RECORD
