Metadata-Version: 2.4
Name: zonefinder
Version: 0.0.5
Summary: Data-driven approach to highlight critical price zones
Home-page: https://www.developexx.com
Author: Anthony Gocmen
Author-email: anthony.gocmen@gmail.com
License: MIT
Requires-Python: >=3.11
License-File: LICENCE
Requires-Dist: pandas>=1.0
Dynamic: author
Dynamic: author-email
Dynamic: description
Dynamic: description-content-type
Dynamic: home-page
Dynamic: license
Dynamic: license-file
Dynamic: requires-dist
Dynamic: requires-python
Dynamic: summary
